ssb_utdanning/__init__.py
ssb_utdanning/config.py
ssb_utdanning/data/__init__.py
ssb_utdanning/data/dtypes.py
ssb_utdanning/data/utd_data.py
ssb_utdanning/format/__init__.py
ssb_utdanning/format/formats.py
ssb_utdanning/format/sas_format_parsing.py
ssb_utdanning/katalog/__init__.py
ssb_utdanning/katalog/katalog.py
ssb_utdanning/katalog/katalog_utils.py
ssb_utdanning/katalog/kataloger/__init__.py
ssb_utdanning/katalog/kataloger/nuskat.py
ssb_utdanning/katalog/kataloger/skoleregister.py
ssb_utdanning/orgnrkontroll/__init__.py
ssb_utdanning/orgnrkontroll/orgnrkontroll.py
ssb_utdanning/orgnrkontroll/to_do.md
ssb_utdanning/paths/__init__.py
ssb_utdanning/paths/get_paths.py
ssb_utdanning/paths/versioning.py
ssb_utdanning/py.typed
ssb_utdanning/utdanning_logger.py
ssb_utdanning-0.0.3.dist-info/LICENSE
ssb_utdanning-0.0.3.dist-info/METADATA
ssb_utdanning-0.0.3.dist-info/WHEEL
ssb_utdanning-0.0.3.dist-info/entry_points.txt
ssb_utdanning-0.0.3.dist-info/RECORD
