Metadata-Version: 2.1
Name: ssb-utdanning
Version: 0.0.3
Summary: SSB Utdanning Fellesfunksjoner
Home-page: https://github.com/statisticsnorway/ssb-utdanning
License: MIT
Author: Carl F. Corneil
Author-email: cfc@ssb.no
Requires-Python: >=3.10,<3.13
Classifier: Development Status :: 2 - Pre-Alpha
Classifier: License :: OSI Approved :: MIT License
Classifier: Programming Language :: Python :: 3
Classifier: Programming Language :: Python :: 3.10
Classifier: Programming Language :: Python :: 3.11
Classifier: Programming Language :: Python :: 3.12
Requires-Dist: cloudpathlib[gs] (>=0.17.0)
Requires-Dist: colorama (>=0.4.6)
Requires-Dist: dapla-toolbelt (>=2.0.6)
Requires-Dist: ipysheet (>=0.7.0,<0.8.0)
Requires-Dist: pandas (>=2.2.0,<3.0.0)
Requires-Dist: pandas-stubs (>=2.2.1.240316)
Requires-Dist: python-dateutil (>=2.8.2,<3.0.0)
Requires-Dist: ssb-datadoc (>=0.12.0,<0.13.0)
Requires-Dist: ssb-fagfunksjoner (>=0.1.0)
Requires-Dist: toml (>=0.10.2)
Requires-Dist: types-colorama (>=0.4.15.20240205)
Requires-Dist: types-python-dateutil (>=2.8.19.14)
Requires-Dist: types-toml (>=0.10.8.7)
Project-URL: Changelog, https://github.com/statisticsnorway/ssb-utdanning/releases
Project-URL: Documentation, https://statisticsnorway.github.io/ssb-utdanning
Project-URL: Repository, https://github.com/statisticsnorway/ssb-utdanning
